setup_client.py
client/__init__.py
client/add_contact.py
client/client_database.py
client/client_main.py
client/del_contact.py
client/main_window.py
client/main_window_conv.py
client/start_dialog.py
include/__init__.py
include/decorators.py
include/descriptors.py
include/errors.py
include/metaclasses.py
include/protocol.py
include/utils.py
include/variables.py
log_configs/__init__.py
log_configs/client_log_config.py
messenger_client_gb_Aikin.egg-info/PKG-INFO
messenger_client_gb_Aikin.egg-info/SOURCES.txt
messenger_client_gb_Aikin.egg-info/dependency_links.txt
messenger_client_gb_Aikin.egg-info/requires.txt
messenger_client_gb_Aikin.egg-info/top_level.txt
unit_tests/__init__.py
unit_tests/test_client.py
unit_tests/test_server.py
unit_tests/test_utils.py